nihao/__init__.py
nihao/api.py
nihao-0.1.1.dist-info/LICENSE
nihao-0.1.1.dist-info/METADATA
nihao-0.1.1.dist-info/WHEEL
nihao-0.1.1.dist-info/top_level.txt
nihao-0.1.1.dist-info/RECORD
