Metadata-Version: 2.1
Name: nihao
Version: 0.1.1
Summary: 中文识别包
Home-page: https://github.com/czcaiwj/chinese
Author: 蔡炜桀
Author-email: justcoding@qq.com
License: UNKNOWN
Platform: UNKNOWN
Classifier: Programming Language :: Python
Classifier: License :: OSI Approved :: MIT License
Classifier: Operating System :: OS Independent
Requires-Python: >=3.6
